django_render_as_template-1.0.0.dist-info/DESCRIPTION.rst
django_render_as_template-1.0.0.dist-info/WHEEL
django_render_as_template-1.0.0.dist-info/top_level.txt
django_render_as_template-1.0.0.dist-info/metadata.json
django_render_as_template-1.0.0.dist-info/METADATA
django_render_as_template-1.0.0.dist-info/RECORD
render_as_template/__init__.py
render_as_template/templatetags/render_as_template.py
render_as_template/templatetags/__init__.py
