Metadata-Version: 2.0
Name: django-render-as-template
Version: 1.0.0
Summary: A template tag for Django that takes a string and renders as it if it was a template.
Home-page: https://github.com/daniboy/django-render-as-template
Author: Daniel Rozenberg
Author-email: me@danielrozenberg.com
License: ISC
Keywords: template templates template-engine flatpages
Platform: UNKNOWN
Classifier: Development Status :: 5 - Production/Stable
Classifier: Framework :: Django
Classifier: Framework :: Django :: 1.8
Classifier: Intended Audience :: Developers
Classifier: Intended Audience :: End Users/Desktop
Classifier: License :: OSI Approved :: ISC License (ISCL)
Classifier: Programming Language :: Python :: 2
Classifier: Programming Language :: Python :: 2.6
Classifier: Programming Language :: Python :: 2.7
Classifier: Programming Language :: Python :: 3
Classifier: Programming Language :: Python :: 3.2
Classifier: Programming Language :: Python :: 3.3
Classifier: Programming Language :: Python :: 3.4
Requires-Dist: django
